communityone/__init__.py
communityone-1.1.1.dist-info/licenses/LICENSE
communityone-1.1.1.dist-info/METADATA
communityone-1.1.1.dist-info/WHEEL
communityone-1.1.1.dist-info/top_level.txt
communityone-1.1.1.dist-info/RECORD
