Metadata-Version: 2.4
Name: communityone
Version: 1.1.1
Summary: Official Python SDK for CommunityOne API
Home-page: https://github.com/CommunityOne-io/communityone-sdk
Author: CommunityOne
Author-email: support@communityone.io
License: MIT
Project-URL: Homepage, https://communityone.io
Project-URL: Documentation, https://api.communityone.io/v1/documentation
Project-URL: Bug Tracker, https://github.com/CommunityOne-io/communityone-sdk/issues
Classifier: Development Status :: 4 - Beta
Classifier: Intended Audience :: Developers
Classifier: License :: OSI Approved :: MIT License
Classifier: Operating System :: OS Independent
Classifier: Programming Language :: Python :: 3
Classifier: Programming Language :: Python :: 3.7
Classifier: Programming Language :: Python :: 3.8
Classifier: Programming Language :: Python :: 3.9
Classifier: Programming Language :: Python :: 3.10
Classifier: Programming Language :: Python :: 3.11
Requires-Python: >=3.7
License-File: LICENSE
Requires-Dist: requests>=2.25.0
Requires-Dist: aiohttp>=3.8.0
Dynamic: author
Dynamic: author-email
Dynamic: classifier
Dynamic: description
Dynamic: description-content-type
Dynamic: home-page
Dynamic: license
Dynamic: license-file
Dynamic: project-url
Dynamic: requires-dist
Dynamic: requires-python
Dynamic: summary
